funcnodes_plotly/__init__.py
funcnodes_plotly/colors.py
funcnodes_plotly/express.py
funcnodes_plotly/figure.py
funcnodes_plotly/layout.py
funcnodes_plotly/plots.py
funcnodes_plotly/utils.py
funcnodes_plotly/react_plugin/index.iife.js
funcnodes_plotly/react_plugin/main.js.LICENSE.txt
funcnodes_plotly/react_plugin/plotly-3.1.0.min.js
funcnodes_plotly/react_plugin/plugin-custom-renders.css
funcnodes_plotly-1.1.0.dist-info/METADATA
funcnodes_plotly-1.1.0.dist-info/WHEEL
funcnodes_plotly-1.1.0.dist-info/entry_points.txt
funcnodes_plotly-1.1.0.dist-info/licenses/LICENSE
funcnodes_plotly-1.1.0.dist-info/RECORD
