Metadata-Version: 2.4
Name: funcnodes-plotly
Version: 1.1.0
Project-URL: homepage, https://github.com/Linkdlab/funcnodes_plotly
Project-URL: source, https://github.com/Linkdlab/funcnodes_plotly
Project-URL: tracker, https://github.com/Linkdlab/funcnodes_plotly/issues
Project-URL: download, https://pypi.org/project/funcnodes-plotly/#files
Author-email: Julian Kimmig <julian.kimmig@gmx.net>
License: AGPL-3.0
License-File: LICENSE
Classifier: License :: OSI Approved :: GNU Affero General Public License v3 or later (AGPLv3+)
Classifier: Programming Language :: Python :: 3
Requires-Python: >=3.11
Requires-Dist: funcnodes
Requires-Dist: funcnodes-core>=0.3.51
Requires-Dist: funcnodes-images
Requires-Dist: funcnodes-pandas>=0.2.3
Requires-Dist: plotly[kaleido]>=6.0.0
